exxablock/__init__.py
exxablock/__main__.py
exxablock/analyticCache.py
exxablock/analyticCli.py
exxablock/common.py
exxablock/executionCache.py
exxablock/executionCli.py
exxablock/histIndexApi.py
exxablock/histIndexCli.py
exxablock/indexCache.py
exxablock/indexCli.py
exxablock/realtimeAnalyticFeed.py
exxablock/realtimeExecutionFeed.py
exxablock/realtimeIndexFeed.py
exxablock/redisCli.py
exxablock-0.0.19.dist-info/LICENSE
exxablock-0.0.19.dist-info/METADATA
exxablock-0.0.19.dist-info/WHEEL
exxablock-0.0.19.dist-info/top_level.txt
exxablock-0.0.19.dist-info/RECORD
