Metadata-Version: 2.1
Name: exxablock
Version: 0.0.19
Summary: ExxaBlock cryptocurrency index, analytic, and execution package
Home-page: https://github.com/exxablock/python/exxablock
Author: Sunwoo Park
Author-email: spark@exxablock.com
License: UNKNOWN
Keywords: [cryptocurrency,bitcoin,blockchain,index,realtime,analytics ]
Platform: UNKNOWN
Classifier: License :: OSI Approved :: MIT License
Classifier: Programming Language :: Python :: 2
Classifier: Programming Language :: Python :: 2.7
Requires-Dist: redis
Requires-Dist: socketIO-client-nexus
